mariner_stats/__init__.py
mariner_stats/estimator.py
mariner_stats-0.1.9.dist-info/METADATA
mariner_stats-0.1.9.dist-info/WHEEL
mariner_stats-0.1.9.dist-info/top_level.txt
mariner_stats-0.1.9.dist-info/RECORD
