Metadata-Version: 2.4
Name: mariner-stats
Version: 0.1.9
Summary: MARINER: marginal selection + UniLasso with interactions.
Author: Aymen Echarghaoui
License: MIT
Keywords: lasso,feature-selection,interactions,regression,scikit-learn
Classifier: Programming Language :: Python :: 3
Classifier: License :: OSI Approved :: MIT License
Classifier: Intended Audience :: Science/Research
Classifier: Topic :: Scientific/Engineering
Requires-Python: >=3.9
Requires-Dist: hiutils-aymen>=0.1.9
